interlinked/__init__.py
interlinked/__main__.py
interlinked/cli.py
interlinked/exceptions.py
interlinked/provider.py
interlinked/router.py
interlinked/workflow.py
interlinked-0.4.0.dist-info/METADATA
interlinked-0.4.0.dist-info/WHEEL
interlinked-0.4.0.dist-info/entry_points.txt
interlinked-0.4.0.dist-info/top_level.txt
interlinked-0.4.0.dist-info/RECORD
