Metadata-Version: 2.1
Name: interlinked
Version: 0.4.0
Summary: Interlinked provides routing, dependency management and dependency
